django_yunohost_integration/__init__.py
django_yunohost_integration/__main__.py
django_yunohost_integration/apps.py
django_yunohost_integration/base_settings.py
django_yunohost_integration/compat.py
django_yunohost_integration/constants.py
django_yunohost_integration/local_settings_source.py
django_yunohost_integration/local_test.py
django_yunohost_integration/path_utils.py
django_yunohost_integration/secret_key.py
django_yunohost_integration/system_checks.py
django_yunohost_integration/test_utils.py
django_yunohost_integration/yunohost_utils.py
django_yunohost_integration/cli_dev/__init__.py
django_yunohost_integration/cli_dev/code_style.py
django_yunohost_integration/cli_dev/local_test.py
django_yunohost_integration/cli_dev/packaging.py
django_yunohost_integration/cli_dev/testing.py
django_yunohost_integration/cli_dev/update_readme_history.py
django_yunohost_integration/management/__init__.py
django_yunohost_integration/management/commands/__init__.py
django_yunohost_integration/management/commands/create_superuser.py
django_yunohost_integration/sso_auth/__init__.py
django_yunohost_integration/sso_auth/auth_backend.py
django_yunohost_integration/sso_auth/auth_middleware.py
django_yunohost_integration/sso_auth/user_profile.py
django_yunohost_integration/tests/__init__.py
django_yunohost_integration/tests/test_django_ynh.py
django_yunohost_integration/tests/test_doctests.py
django_yunohost_integration/tests/test_manage.py
django_yunohost_integration/tests/test_project_setup.py
django_yunohost_integration/tests/test_readme.py
django_yunohost_integration/tests/test_readme_history.py
django_yunohost_integration/tests/test_system_checks.py
django_yunohost_integration/tests/test_utils.py
django_yunohost_integration/tests/test_yunohost_utils.py
django_yunohost_integration/yunohost/__init__.py
django_yunohost_integration/yunohost/ynh_jwt.py
django_yunohost_integration/yunohost/tests/__init__.py
django_yunohost_integration/yunohost/tests/test_ynh_jwt.py
django_yunohost_integration-0.10.9.dist-info/METADATA
django_yunohost_integration-0.10.9.dist-info/WHEEL
django_yunohost_integration-0.10.9.dist-info/entry_points.txt
django_yunohost_integration-0.10.9.dist-info/licenses/LICENSE
django_yunohost_integration-0.10.9.dist-info/RECORD
