Metadata-Version: 2.4
Name: django_yunohost_integration
Version: 0.10.9
Summary: Glue code to package django projects as yunohost apps.
Project-URL: Documentation, https://github.com/YunoHost-Apps/django_yunohost_integration
Project-URL: Source, https://github.com/YunoHost-Apps/django_yunohost_integration
Author-email: Jens Diemer <git@jensdiemer.de>
License: GPL-3.0-or-later
License-File: LICENSE
Requires-Python: <3.14,>=3.11
Requires-Dist: cli-base-utilities>=0.17.0
Requires-Dist: colorlog
Requires-Dist: django-tools
Requires-Dist: django<5.2
Requires-Dist: packaging
Requires-Dist: pyjwt
Requires-Dist: pyyaml
Requires-Dist: tyro
